{
  "File" : "part-00003-9aa8ec4a-3763-4967-be92-2507c58a6b83-c000.snappy.orc",
  "Compression" : "SNAPPY",
  "Column_types" : "struct<store_id:int,store_name:string,latitude:double,longitude:double>",
  "Number_of_rows" : 163556,
  "Number_of_stripes" : 1,
  "Stripes" : [ {
    "Stripe" : 0,
    "Row_count" : 163556,
    "columns" : [ {
      "column" : "store_id",
      "nulls" : 0,
      "value_count" : 163556,
      "min" : "496164",
      "max" : "659719"
    }, {
      "column" : "store_name",
      "nulls" : 0,
      "value_count" : 163556,
      "min" : null,
      "max" : null
    }, {
      "column" : "latitude",
      "nulls" : 0,
      "value_count" : 163556,
      "min" : "-47.528241",
      "max" : "73.471473"
    }, {
      "column" : "longitude",
      "nulls" : 0,
      "value_count" : 163556,
      "min" : "17.095074",
      "max" : "138.093138"
    } ]
  } ]
}